build/lib/sksound/__init__.py
build/lib/sksound/misc.py
build/lib/sksound/sounds.py
sksound/__init__.py
sksound/misc.py
sksound/sounds.py
tests/YouAreNotIt.mp3
tests/YouAreNotIt.wav
tests/__init__.py
tests/a1.wav
tests/float_sound.wav
tests/peas.wav
tests/test_sound.py
tests/tiger.wav
tests/tmp.wav
scikit_sound-0.3.2.dist-info/METADATA
scikit_sound-0.3.2.dist-info/WHEEL
scikit_sound-0.3.2.dist-info/licenses/LICENSE.txt
scikit_sound-0.3.2.dist-info/RECORD
