Metadata-Version: 2.4
Name: scikit-sound
Version: 0.3.2
Summary: Python utilites for working with sound signals
Project-URL: Homepage, http://work.thaslwanter.at/sksound/html
Project-URL: Repository, https://github.com/thomas-haslwanter/scikit-sound
Author-email: Thomas Haslwanter <thomas.haslwanter@fh-ooe.at>
License-Expression: BSD-3-Clause
License-File: LICENSE.txt
Keywords: auditory signals,sound
Classifier: Development Status :: 4 - Beta
Classifier: Intended Audience :: Developers
Classifier: Intended Audience :: Science/Research
Classifier: License :: OSI Approved :: BSD License
Classifier: Programming Language :: Python :: 3
Classifier: Topic :: Scientific/Engineering
Requires-Python: >=3.9
Requires-Dist: appdirs>=1.4.3
Requires-Dist: docutils>=0.3
Requires-Dist: numpy>=1.13.0
Requires-Dist: pygame>=2.0; sys_platform == 'linux'
Requires-Dist: pyyaml>=5.3.1
Requires-Dist: scipy>=1.5
